pyfmdvrp/__init__.py
pyfmdvrp/env.py
pyfmdvrp/engine/__init__.py
pyfmdvrp/engine/city.py
pyfmdvrp/engine/depot.py
pyfmdvrp/engine/manager.py
pyfmdvrp/engine/status.py
pyfmdvrp/engine/vehicle.py
pyfmdvrp/utils/__init__.py
pyfmdvrp/utils/action_space.py
pyfmdvrp/utils/generate_problem.py
pyfmdvrp/utils/obeservation.py
pyfmdvrp/utils/rewards.py
pyfmdvrp/utils/visualization.py
pyfmdvrp-0.0.0.1.dist-info/METADATA
pyfmdvrp-0.0.0.1.dist-info/WHEEL
pyfmdvrp-0.0.0.1.dist-info/top_level.txt
pyfmdvrp-0.0.0.1.dist-info/RECORD
